{
  "slug": "datadog",
  "area": "projects",
  "status": "refined",
  "action": "refine",
  "average": 4.11,
  "reject_count": 0,
  "needs_refine_count": 1,
  "pass_count": 2,
  "weakest_sections": [
    {
      "reviewer": "zero-base",
      "section": "## 实践案例",
      "verdict": "pass"
    },
    {
      "reviewer": "academic",
      "section": "## 为什么重要",
      "verdict": "pass"
    },
    {
      "reviewer": "engineer",
      "section": "## 踩过的坑",
      "verdict": "needs-refine"
    }
  ],
  "fix_hints": [
    {
      "reviewer": "engineer",
      "hint": "APM pitfall says 1000 hosts add 31万, but $31-40/host/month is about 3.1-4万美元; fix arithmetic to avoid a billing misconception."
    }
  ],
  "reviews": [
    {
      "reviewer": "zero-base",
      "scores": {
        "analogy": 4,
        "accessibility": 5,
        "case_clarity": 5
      },
      "average": 4.67,
      "verdict": "pass",
      "weakest_section": "## 实践案例",
      "fix_hints": []
    },
    {
      "reviewer": "academic",
      "scores": {
        "fact_accuracy": 4,
        "citation_correctness": 4,
        "no_distortion": 4
      },
      "average": 4,
      "verdict": "pass",
      "weakest_section": "## 为什么重要",
      "fix_hints": []
    },
    {
      "reviewer": "engineer",
      "scores": {
        "code_runnable": 4,
        "pitfalls_useful": 3,
        "scope_correct": 4
      },
      "average": 3.67,
      "verdict": "needs-refine",
      "weakest_section": "## 踩过的坑",
      "fix_hints": [
        "APM pitfall says 1000 hosts add 31万, but $31-40/host/month is about 3.1-4万美元; fix arithmetic to avoid a billing misconception."
      ]
    }
  ],
  "refinement": {
    "status": "refined",
    "round": 1,
    "sections_modified": [
      "## 为什么重要",
      "## 踩过的坑"
    ],
    "unresolved_hints": []
  },
  "quality_gate": {
    "pass": true,
    "l1_pass": true,
    "lines": 158,
    "reasons": []
  },
  "lines": 158,
  "l1_pass": true
}
