{
  "action": "refine",
  "average": 4.11,
  "reject_count": 0,
  "needs_refine_count": 3,
  "pass_count": 0,
  "weakest_sections": [
    {
      "reviewer": "zero-base",
      "section": "## 实践案例",
      "verdict": "needs-refine"
    },
    {
      "reviewer": "academic",
      "section": "## 为什么重要",
      "verdict": "needs-refine"
    },
    {
      "reviewer": "engineer",
      "section": "## 实践案例",
      "verdict": "needs-refine"
    }
  ],
  "fix_hints": [
    {
      "reviewer": "zero-base",
      "hint": "案例 3 只有文字描述、没有代码块和逐部分解释；应给出改 step id 前后的对照代码，说明缓存为何失效"
    },
    {
      "reviewer": "academic",
      "hint": "「trigger.dev V3 … 把 step.run 抄进了自己的 SDK」表述过满，宜改为「也采用了类似的 step.run 风格 API」，避免写成抄袭指控"
    },
    {
      "reviewer": "engineer",
      "hint": "案例 3 缺可跟做代码；反向链接段被手写列表占满，应恢复 regen 占位注释并清空手工条目"
    }
  ],
  "reviews": [
    {
      "reviewer": "zero-base",
      "scores": {
        "analogy": 5,
        "accessibility": 4,
        "case_clarity": 3
      },
      "average": 4,
      "verdict": "needs-refine",
      "weakest_section": "## 实践案例",
      "fix_hints": [
        "案例 3 只有文字描述、没有代码块和逐部分解释；应给出改 step id 前后的对照代码，说明缓存为何失效"
      ]
    },
    {
      "reviewer": "academic",
      "scores": {
        "fact_accuracy": 4,
        "citation_correctness": 5,
        "no_distortion": 3
      },
      "average": 4,
      "verdict": "needs-refine",
      "weakest_section": "## 为什么重要",
      "fix_hints": [
        "「trigger.dev V3 … 把 step.run 抄进了自己的 SDK」表述过满，宜改为「也采用了类似的 step.run 风格 API」，避免写成抄袭指控"
      ]
    },
    {
      "reviewer": "engineer",
      "scores": {
        "code_runnable": 3,
        "pitfalls_useful": 5,
        "scope_correct": 5
      },
      "average": 4.33,
      "verdict": "needs-refine",
      "weakest_section": "## 实践案例",
      "fix_hints": [
        "案例 3 缺可跟做代码；反向链接段被手写列表占满，应恢复 regen 占位注释并清空手工条目"
      ]
    }
  ]
}
