{
  "action": "refine",
  "average": 3.67,
  "reject_count": 0,
  "needs_refine_count": 3,
  "pass_count": 0,
  "weakest_sections": [
    {
      "reviewer": "zero-base",
      "section": "## 实践案例",
      "verdict": "needs-refine"
    },
    {
      "reviewer": "academic",
      "section": "## 为什么重要",
      "verdict": "needs-refine"
    },
    {
      "reviewer": "engineer",
      "section": "## 实践案例",
      "verdict": "needs-refine"
    }
  ],
  "fix_hints": [
    {
      "reviewer": "zero-base",
      "hint": "轿车 vs 多马达电车、小房间、广播电台类比够用，LiveView「遥控器/电视台」可再贴紧一点"
    },
    {
      "reviewer": "zero-base",
      "hint": "BEAM / PubSub / OTP 有桥接，但案例 1 缺 render，零基础看不到消息怎么画到页面上"
    },
    {
      "reviewer": "zero-base",
      "hint": "案例 2 把 router 的 channel 声明和 defmodule 揉在同一代码块，步骤跳跃，建议拆开并补一句「浏览器 join topic 后才能收到」"
    },
    {
      "reviewer": "academic",
      "hint": "来源 phoenixframework/phoenix 正确；LiveView 2018 预览、HEEx 时间线大致可核验"
    },
    {
      "reviewer": "academic",
      "hint": "「Discord、Pinterest 早期用 Elixir/Phoenix」易误读：Discord 实时栈主打 Elixir/OTP，Pinterest 通知亦偏 Elixir——应弱化为 Elixir/OTP（Phoenix 为同生态 web 层），避免写成两家都深度用 Phoenix"
    },
    {
      "reviewer": "academic",
      "hint": "「一台机器 200 万 WebSocket」有官方博客支撑，可保留但宜标明是 benchmark 场景而非默认业务数字"
    },
    {
      "reviewer": "engineer",
      "hint": "案例 1 LiveView 缺 render/1，跟做无法看到 messages 如何输出；建议补最小 HEEx 列表"
    },
    {
      "reviewer": "engineer",
      "hint": "踩坑里「Redis/PG2」：现代 OTP 更常用 :pg / Redis/Postgres PubSub 适配器，建议改掉过时 PG2 写法"
    },
    {
      "reviewer": "engineer",
      "hint": "适用/不适用已区分实时/LiveView vs CPU 密集/生态缺失；边界够用"
    }
  ],
  "reviews": [
    {
      "reviewer": "zero-base",
      "scores": {
        "analogy": 4,
        "accessibility": 4,
        "case_clarity": 3
      },
      "average": 3.67,
      "verdict": "needs-refine",
      "weakest_section": "## 实践案例",
      "fix_hints": [
        "轿车 vs 多马达电车、小房间、广播电台类比够用，LiveView「遥控器/电视台」可再贴紧一点",
        "BEAM / PubSub / OTP 有桥接，但案例 1 缺 render，零基础看不到消息怎么画到页面上",
        "案例 2 把 router 的 channel 声明和 defmodule 揉在同一代码块，步骤跳跃，建议拆开并补一句「浏览器 join topic 后才能收到」"
      ]
    },
    {
      "reviewer": "academic",
      "scores": {
        "fact_accuracy": 3,
        "citation_correctness": 5,
        "no_distortion": 3
      },
      "average": 3.67,
      "verdict": "needs-refine",
      "weakest_section": "## 为什么重要",
      "fix_hints": [
        "来源 phoenixframework/phoenix 正确；LiveView 2018 预览、HEEx 时间线大致可核验",
        "「Discord、Pinterest 早期用 Elixir/Phoenix」易误读：Discord 实时栈主打 Elixir/OTP，Pinterest 通知亦偏 Elixir——应弱化为 Elixir/OTP（Phoenix 为同生态 web 层），避免写成两家都深度用 Phoenix",
        "「一台机器 200 万 WebSocket」有官方博客支撑，可保留但宜标明是 benchmark 场景而非默认业务数字"
      ]
    },
    {
      "reviewer": "engineer",
      "scores": {
        "code_runnable": 3,
        "pitfalls_useful": 4,
        "scope_correct": 4
      },
      "average": 3.67,
      "verdict": "needs-refine",
      "weakest_section": "## 实践案例",
      "fix_hints": [
        "案例 1 LiveView 缺 render/1，跟做无法看到 messages 如何输出；建议补最小 HEEx 列表",
        "踩坑里「Redis/PG2」：现代 OTP 更常用 :pg / Redis/Postgres PubSub 适配器，建议改掉过时 PG2 写法",
        "适用/不适用已区分实时/LiveView vs CPU 密集/生态缺失；边界够用"
      ]
    }
  ]
}
