{
  "action": "refine",
  "average": 4.22,
  "reject_count": 0,
  "needs_refine_count": 1,
  "pass_count": 2,
  "weakest_sections": [
    {
      "reviewer": "zero-base",
      "section": "## 实践案例",
      "verdict": "needs-refine"
    },
    {
      "reviewer": "academic",
      "section": "## 关联",
      "verdict": "pass"
    },
    {
      "reviewer": "engineer",
      "section": "## 实践案例",
      "verdict": "pass"
    }
  ],
  "fix_hints": [
    {
      "reviewer": "zero-base",
      "hint": "案例 3 只有一行命令和两句说明，缺逐步解释：chosen/rejected 数据长什么样、loss 和 LoRA recipe 差在哪"
    },
    {
      "reviewer": "zero-base",
      "hint": "案例 1/2 有说明但未按「逐部分解释」拆开，零基础不易对照命令每一段在干什么"
    },
    {
      "reviewer": "academic",
      "hint": "关联里 [[hindley-milner]] 与 YAML/dataclass 类型推导的类比牵强，易把 HM 类型系统误读成配置解析技巧"
    },
    {
      "reviewer": "engineer",
      "hint": "案例 3 可补一行示意 DPO 数据字段（chosen/rejected）或说明需自备偏好对数据集，否则跟做时会卡在数据格式"
    }
  ],
  "reviews": [
    {
      "reviewer": "zero-base",
      "scores": {
        "analogy": 4,
        "accessibility": 4,
        "case_clarity": 3
      },
      "average": 3.67,
      "verdict": "needs-refine",
      "weakest_section": "## 实践案例",
      "fix_hints": [
        "案例 3 只有一行命令和两句说明，缺逐步解释：chosen/rejected 数据长什么样、loss 和 LoRA recipe 差在哪",
        "案例 1/2 有说明但未按「逐部分解释」拆开，零基础不易对照命令每一段在干什么"
      ]
    },
    {
      "reviewer": "academic",
      "scores": {
        "fact_accuracy": 5,
        "citation_correctness": 4,
        "no_distortion": 4
      },
      "average": 4.33,
      "verdict": "pass",
      "weakest_section": "## 关联",
      "fix_hints": [
        "关联里 [[hindley-milner]] 与 YAML/dataclass 类型推导的类比牵强，易把 HM 类型系统误读成配置解析技巧"
      ]
    },
    {
      "reviewer": "engineer",
      "scores": {
        "code_runnable": 4,
        "pitfalls_useful": 5,
        "scope_correct": 5
      },
      "average": 4.67,
      "verdict": "pass",
      "weakest_section": "## 实践案例",
      "fix_hints": [
        "案例 3 可补一行示意 DPO 数据字段（chosen/rejected）或说明需自备偏好对数据集，否则跟做时会卡在数据格式"
      ]
    }
  ]
}
