{
  "action": "refine",
  "average": 4.11,
  "reject_count": 0,
  "needs_refine_count": 2,
  "pass_count": 1,
  "weakest_sections": [
    {
      "reviewer": "zero-base",
      "section": "## 实践案例",
      "verdict": "needs-refine"
    },
    {
      "reviewer": "academic",
      "section": "## 学到什么",
      "verdict": "pass"
    },
    {
      "reviewer": "engineer",
      "section": "## 实践案例",
      "verdict": "needs-refine"
    }
  ],
  "fix_hints": [
    {
      "reviewer": "zero-base",
      "hint": "案例2把 ctags|jq|fzf|bat|vim 串成一行，零基础跟不住；拆成「生成 JSON → 抽出三列 → fzf 选中 → 打开文件」四步并逐行解释字段"
    },
    {
      "reviewer": "zero-base",
      "hint": "案例4 --_interactive 对入门过陡，可删或改成一句补充，把篇幅留给案例2的逐步解释"
    },
    {
      "reviewer": "academic",
      "hint": "核心要点写「150+ 语言」，学到什么写「160 种」——统一为同一数量表述（如「150+」）"
    },
    {
      "reviewer": "academic",
      "hint": "关联里写 Helix「原生集成 ctags」偏绝对；Helix 主路径是 LSP/tree-sitter，宜改为「也可配合 tags/LSP 双轨」或弱化"
    },
    {
      "reviewer": "engineer",
      "hint": "案例2：jq 输出 path:line 粘在一起后，fzf preview 的 {2} 不是纯路径，enter 的 vim +{2..} {1} 字段也错；应输出 name\\tpath\\tline 三列，preview 用 {2}，vim 用 +{3} {2}"
    },
    {
      "reviewer": "engineer",
      "hint": "案例2 --fields=+n 对 JSON 行号字段的说明可补一句；或改用 JSON 里默认就有的 line 字段并去掉易误导的 flags"
    }
  ],
  "reviews": [
    {
      "reviewer": "zero-base",
      "scores": {
        "analogy": 5,
        "accessibility": 4,
        "case_clarity": 3
      },
      "average": 4,
      "verdict": "needs-refine",
      "weakest_section": "## 实践案例",
      "fix_hints": [
        "案例2把 ctags|jq|fzf|bat|vim 串成一行，零基础跟不住；拆成「生成 JSON → 抽出三列 → fzf 选中 → 打开文件」四步并逐行解释字段",
        "案例4 --_interactive 对入门过陡，可删或改成一句补充，把篇幅留给案例2的逐步解释"
      ]
    },
    {
      "reviewer": "academic",
      "scores": {
        "fact_accuracy": 4,
        "citation_correctness": 5,
        "no_distortion": 4
      },
      "average": 4.33,
      "verdict": "pass",
      "weakest_section": "## 学到什么",
      "fix_hints": [
        "核心要点写「150+ 语言」，学到什么写「160 种」——统一为同一数量表述（如「150+」）",
        "关联里写 Helix「原生集成 ctags」偏绝对；Helix 主路径是 LSP/tree-sitter，宜改为「也可配合 tags/LSP 双轨」或弱化"
      ]
    },
    {
      "reviewer": "engineer",
      "scores": {
        "code_runnable": 3,
        "pitfalls_useful": 5,
        "scope_correct": 4
      },
      "average": 4,
      "verdict": "needs-refine",
      "weakest_section": "## 实践案例",
      "fix_hints": [
        "案例2：jq 输出 path:line 粘在一起后，fzf preview 的 {2} 不是纯路径，enter 的 vim +{2..} {1} 字段也错；应输出 name\\tpath\\tline 三列，preview 用 {2}，vim 用 +{3} {2}",
        "案例2 --fields=+n 对 JSON 行号字段的说明可补一句；或改用 JSON 里默认就有的 line 字段并去掉易误导的 flags"
      ]
    }
  ]
}
