{
  "slug": "belady-1966",
  "area": "papers",
  "status": "refined",
  "action": "refine",
  "average": 3.78,
  "reject_count": 0,
  "needs_refine_count": 2,
  "pass_count": 1,
  "weakest_sections": [
    {
      "reviewer": "zero-base",
      "section": "## 实践案例",
      "verdict": "needs-refine"
    },
    {
      "reviewer": "academic",
      "section": "## 是什么 / ## 为什么重要",
      "verdict": "needs-refine"
    },
    {
      "reviewer": "engineer",
      "section": "## 实践案例",
      "verdict": "pass"
    }
  ],
  "fix_hints": [
    {
      "reviewer": "zero-base",
      "hint": "实践案例只有两个，第三个现代小缓存例子缺失；核心要点也应更贴近 1/2/3 三点结构。"
    },
    {
      "reviewer": "academic",
      "hint": "1966 论文贡献和 1969 FIFO anomaly 后续工作容易被读成同一篇结果；来源字段含逗号和引号，应按 base rules 单引号包裹。"
    }
  ],
  "reviews": [
    {
      "reviewer": "zero-base",
      "scores": {
        "analogy": 4,
        "accessibility": 4,
        "case_clarity": 3
      },
      "average": 3.67,
      "verdict": "needs-refine",
      "weakest_section": "## 实践案例",
      "fix_hints": [
        "实践案例只有两个，第三个现代小缓存例子缺失；核心要点也应更贴近 1/2/3 三点结构。"
      ]
    },
    {
      "reviewer": "academic",
      "scores": {
        "fact_accuracy": 4,
        "citation_correctness": 3,
        "no_distortion": 4
      },
      "average": 3.67,
      "verdict": "needs-refine",
      "weakest_section": "## 是什么 / ## 为什么重要",
      "fix_hints": [
        "1966 论文贡献和 1969 FIFO anomaly 后续工作容易被读成同一篇结果；来源字段含逗号和引号，应按 base rules 单引号包裹。"
      ]
    },
    {
      "reviewer": "engineer",
      "scores": {
        "code_runnable": 4,
        "pitfalls_useful": 4,
        "scope_correct": 4
      },
      "average": 4,
      "verdict": "pass",
      "weakest_section": "## 实践案例",
      "fix_hints": []
    }
  ],
  "refinement": {
    "action": "refine",
    "sections_modified": [
      "frontmatter",
      "## 为什么重要",
      "## 核心要点",
      "## 实践案例"
    ],
    "unresolved_hints": []
  },
  "quality_gate": {
    "pass": true,
    "l1_pass": true,
    "lines": 170,
    "reasons": []
  }
}
