{
  "action": "refine",
  "average": 4,
  "reject_count": 0,
  "needs_refine_count": 1,
  "pass_count": 2,
  "weakest_sections": [
    {
      "reviewer": "zero-base",
      "section": "## 核心要点",
      "verdict": "pass"
    },
    {
      "reviewer": "academic",
      "section": "## 实践案例",
      "verdict": "needs-refine"
    },
    {
      "reviewer": "engineer",
      "section": "## 实践案例",
      "verdict": "pass"
    }
  ],
  "fix_hints": [
    {
      "reviewer": "academic",
      "hint": "案例 3 写规则引擎转发到 Kafka，但 EMQX 开源版数据集成仅 HTTP/MQTT，Kafka Sink 属企业版——正文易让人以为开源即可直连 Kafka"
    },
    {
      "reviewer": "academic",
      "hint": "「Erlang 写的 broker 一直碾压 Java/Go」过绝对；宜改成连接密度/长连接场景下的常见优势并加限定"
    },
    {
      "reviewer": "engineer",
      "hint": "案例 3 提到 Kafka 下游时，应显式标注企业版能力，避免选型踩坑"
    }
  ],
  "reviews": [
    {
      "reviewer": "zero-base",
      "scores": {
        "analogy": 5,
        "accessibility": 4,
        "case_clarity": 4
      },
      "average": 4.33,
      "verdict": "pass",
      "weakest_section": "## 核心要点",
      "fix_hints": []
    },
    {
      "reviewer": "academic",
      "scores": {
        "fact_accuracy": 3,
        "citation_correctness": 4,
        "no_distortion": 3
      },
      "average": 3.33,
      "verdict": "needs-refine",
      "weakest_section": "## 实践案例",
      "fix_hints": [
        "案例 3 写规则引擎转发到 Kafka，但 EMQX 开源版数据集成仅 HTTP/MQTT，Kafka Sink 属企业版——正文易让人以为开源即可直连 Kafka",
        "「Erlang 写的 broker 一直碾压 Java/Go」过绝对；宜改成连接密度/长连接场景下的常见优势并加限定"
      ]
    },
    {
      "reviewer": "engineer",
      "scores": {
        "code_runnable": 4,
        "pitfalls_useful": 5,
        "scope_correct": 4
      },
      "average": 4.33,
      "verdict": "pass",
      "weakest_section": "## 实践案例",
      "fix_hints": [
        "案例 3 提到 Kafka 下游时，应显式标注企业版能力，避免选型踩坑"
      ]
    }
  ]
}
