{
  "slug": "gru-2014",
  "area": "papers",
  "status": "passed",
  "action": "pass",
  "average": 4.56,
  "reject_count": 0,
  "needs_refine_count": 0,
  "pass_count": 3,
  "weakest_sections": [
    {
      "reviewer": "zero-base",
      "section": "## 实践案例",
      "verdict": "pass"
    },
    {
      "reviewer": "academic",
      "section": "## 踩过的坑",
      "verdict": "pass"
    },
    {
      "reviewer": "engineer",
      "section": "## 实践案例",
      "verdict": "pass"
    }
  ],
  "fix_hints": [
    {
      "reviewer": "zero-base",
      "hint": "案例 1 只有构造 nn.GRU，缺一行前向/输出形状；案例 2/3 的逐步解释已够托住跟读。"
    },
    {
      "reviewer": "academic",
      "hint": "Cho EMNLP 2014 / Chung 2014 / Sutskever seq2seq / Bahdanau attention 时序与定位正确；『参数少约 25%』为工程约数，可接受。"
    },
    {
      "reviewer": "engineer",
      "hint": "encoder-decoder 伪代码概念正确；reset/update 记反、固定长度 c、SMT 非端到端 NMT 等踩坑可操作；适用有 <100 step 量化边界。"
    }
  ],
  "reviews": [
    {
      "reviewer": "zero-base",
      "scores": {
        "analogy": 5,
        "accessibility": 4,
        "case_clarity": 4
      },
      "average": 4.33,
      "verdict": "pass",
      "weakest_section": "## 实践案例",
      "fix_hints": [
        "案例 1 只有构造 nn.GRU，缺一行前向/输出形状；案例 2/3 的逐步解释已够托住跟读。"
      ]
    },
    {
      "reviewer": "academic",
      "scores": {
        "fact_accuracy": 5,
        "citation_correctness": 5,
        "no_distortion": 4
      },
      "average": 4.67,
      "verdict": "pass",
      "weakest_section": "## 踩过的坑",
      "fix_hints": [
        "Cho EMNLP 2014 / Chung 2014 / Sutskever seq2seq / Bahdanau attention 时序与定位正确；『参数少约 25%』为工程约数，可接受。"
      ]
    },
    {
      "reviewer": "engineer",
      "scores": {
        "code_runnable": 4,
        "pitfalls_useful": 5,
        "scope_correct": 5
      },
      "average": 4.67,
      "verdict": "pass",
      "weakest_section": "## 实践案例",
      "fix_hints": [
        "encoder-decoder 伪代码概念正确；reset/update 记反、固定长度 c、SMT 非端到端 NMT 等踩坑可操作；适用有 <100 step 量化边界。"
      ]
    }
  ],
  "quality_gate": {
    "pass": true,
    "l1_pass": true,
    "lines": 171,
    "reasons": []
  },
  "lines": 171,
  "l1_pass": true
}
