{
  "slug": "ingres-1976",
  "area": "papers",
  "status": "passed",
  "action": "pass",
  "average": 4.67,
  "reject_count": 0,
  "needs_refine_count": 0,
  "pass_count": 3,
  "weakest_sections": [
    {
      "reviewer": "zero-base",
      "section": "## 踩过的坑",
      "verdict": "pass"
    },
    {
      "reviewer": "academic",
      "section": "## 是什么",
      "verdict": "pass"
    },
    {
      "reviewer": "engineer",
      "section": "## 实践案例",
      "verdict": "pass"
    }
  ],
  "fix_hints": [
    {
      "reviewer": "zero-base",
      "hint": "米其林/食堂类比贴合；QUEL/查询修改/分解桥接清楚；三案例均有逐部分解释。"
    },
    {
      "reviewer": "academic",
      "hint": "TODS 1976 作者与 QUEL、query modification、decomposition、多进程架构与原文一致；Postgres/Sybase 血脉叙述合理。Informix 与 INGRES 团队关系略简化，教学可接受。"
    },
    {
      "reviewer": "engineer",
      "hint": "QUEL 示例可跟读；商业输给 SQL、进程架构过时、两表分解、并发弱等踩坑具体；适用边界锚定 1976 时间点。"
    }
  ],
  "reviews": [
    {
      "reviewer": "zero-base",
      "scores": {
        "analogy": 5,
        "accessibility": 5,
        "case_clarity": 5
      },
      "average": 5,
      "verdict": "pass",
      "weakest_section": "## 踩过的坑",
      "fix_hints": [
        "米其林/食堂类比贴合；QUEL/查询修改/分解桥接清楚；三案例均有逐部分解释。"
      ]
    },
    {
      "reviewer": "academic",
      "scores": {
        "fact_accuracy": 4,
        "citation_correctness": 5,
        "no_distortion": 4
      },
      "average": 4.33,
      "verdict": "pass",
      "weakest_section": "## 是什么",
      "fix_hints": [
        "TODS 1976 作者与 QUEL、query modification、decomposition、多进程架构与原文一致；Postgres/Sybase 血脉叙述合理。Informix 与 INGRES 团队关系略简化，教学可接受。"
      ]
    },
    {
      "reviewer": "engineer",
      "scores": {
        "code_runnable": 4,
        "pitfalls_useful": 5,
        "scope_correct": 5
      },
      "average": 4.67,
      "verdict": "pass",
      "weakest_section": "## 实践案例",
      "fix_hints": [
        "QUEL 示例可跟读；商业输给 SQL、进程架构过时、两表分解、并发弱等踩坑具体；适用边界锚定 1976 时间点。"
      ]
    }
  ],
  "aggregate": {
    "average": 4.67,
    "verdict": "pass",
    "action": "pass",
    "rejects": 0,
    "needs_refine": 0,
    "all_pass": true
  },
  "refinement": {
    "action": "none",
    "reason": "三审均为 pass，未触发 refiner；quality-gate 已通过。",
    "sections_modified": [],
    "unresolved_hints": []
  },
  "quality_gate": {
    "pass": true,
    "lines": 163,
    "l1_pass": true,
    "reasons": []
  },
  "lines": 163,
  "l1_pass": true
}
