{
  "action": "pass",
  "average": 4.33,
  "reject_count": 0,
  "needs_refine_count": 0,
  "pass_count": 3,
  "weakest_sections": [
    {
      "reviewer": "zero-base",
      "section": "## 实践案例",
      "verdict": "pass"
    },
    {
      "reviewer": "academic",
      "section": "## 学到什么",
      "verdict": "pass"
    },
    {
      "reviewer": "engineer",
      "section": "## 适用 vs 不适用场景",
      "verdict": "pass"
    }
  ],
  "fix_hints": [
    {
      "reviewer": "zero-base",
      "hint": "舞台/跑腿/厨师类比贯穿全文，零基础直觉强"
    },
    {
      "reviewer": "zero-base",
      "hint": "案例 3 里 simulators / policy / trainer 未先定义，跟读时需脑补前置对象；可加一句『假设已有仿真 actor 列表』"
    },
    {
      "reviewer": "zero-base",
      "hint": "GCS / lineage / future 均有日常桥接，可跟住"
    },
    {
      "reviewer": "academic",
      "hint": "来源 Moritz et al. / OSDI 2018 正确；task+actor 同动态任务图、GCS 控面、bottom-up scheduler 与论文一致"
    },
    {
      "reviewer": "academic",
      "hint": "『100 节点上超过 180 万 task/s』与论文报告量级相符"
    },
    {
      "reviewer": "academic",
      "hint": "『之后几年』上层库叙述属合理教学概括，未发现硬伤"
    },
    {
      "reviewer": "engineer",
      "hint": "案例 API（@ray.remote / .remote / ray.get / ray.wait / num_gpus）概念正确，可跟做"
    },
    {
      "reviewer": "engineer",
      "hint": "踩坑具体：别当 Spark、actor 热点、对象不可变、动态图调度局限"
    },
    {
      "reviewer": "engineer",
      "hint": "适用/不适用边界清楚；若再补『单机秒级脚本不必上 Ray』一类量化会更稳，当前已够 pass"
    }
  ],
  "reviews": [
    {
      "reviewer": "zero-base",
      "scores": {
        "analogy": 5,
        "accessibility": 4,
        "case_clarity": 4
      },
      "average": 4.33,
      "verdict": "pass",
      "weakest_section": "## 实践案例",
      "fix_hints": [
        "舞台/跑腿/厨师类比贯穿全文，零基础直觉强",
        "案例 3 里 simulators / policy / trainer 未先定义，跟读时需脑补前置对象；可加一句『假设已有仿真 actor 列表』",
        "GCS / lineage / future 均有日常桥接，可跟住"
      ]
    },
    {
      "reviewer": "academic",
      "scores": {
        "fact_accuracy": 5,
        "citation_correctness": 5,
        "no_distortion": 4
      },
      "average": 4.67,
      "verdict": "pass",
      "weakest_section": "## 学到什么",
      "fix_hints": [
        "来源 Moritz et al. / OSDI 2018 正确；task+actor 同动态任务图、GCS 控面、bottom-up scheduler 与论文一致",
        "『100 节点上超过 180 万 task/s』与论文报告量级相符",
        "『之后几年』上层库叙述属合理教学概括，未发现硬伤"
      ]
    },
    {
      "reviewer": "engineer",
      "scores": {
        "code_runnable": 4,
        "pitfalls_useful": 4,
        "scope_correct": 4
      },
      "average": 4,
      "verdict": "pass",
      "weakest_section": "## 适用 vs 不适用场景",
      "fix_hints": [
        "案例 API（@ray.remote / .remote / ray.get / ray.wait / num_gpus）概念正确，可跟做",
        "踩坑具体：别当 Spark、actor 热点、对象不可变、动态图调度局限",
        "适用/不适用边界清楚；若再补『单机秒级脚本不必上 Ray』一类量化会更稳，当前已够 pass"
      ]
    }
  ],
  "slug": "ray-2018",
  "area": "papers",
  "status": "passed",
  "aggregate": {
    "average": 4.33,
    "verdict": "pass",
    "action": "pass",
    "rejects": 0,
    "needs_refine": 0,
    "all_pass": true,
    "reason": "三位 reviewer 均为 pass，平均分 4.33 >= 4。"
  },
  "quality_gate": {
    "pass": true,
    "lines": 161,
    "l1_pass": true,
    "reasons": []
  },
  "lines": 161,
  "l1_pass": true
}
